{
  "date": "2026-05-05",
  "items": [
    {
      "date": "2026-05-05",
      "sign": "사자자리",
      "rank": 1,
      "shortMessage": "드라마틱한 연애운이에요.",
      "detail": "한눈에 운명을 느낄 수 있는 만남의 예감이 있어요. 영화처럼 드라마틱한 사랑의 기회도 올 수 있어요. 세심하게 메이크업하고 나가세요.",
      "luckyColor": "갈색",
      "luckyItem": "편지지",
      "moneyScore": 5,
      "loveScore": 5,
      "workScore": 4,
      "healthScore": 5
    },
    {
      "date": "2026-05-05",
      "sign": "양자리",
      "rank": 2,
      "shortMessage": "새로운 시작이 좋아요.",
      "detail": "관심 있는 분야를 탐구하고 싶어하는 마음이 커져요. 완전히 새로운 것을 시작해보는 것도 괜찮아요. 설렘으로 오래 지속될 가능성이 커요.",
      "luckyColor": "주황색",
      "luckyItem": "카시와 모찌",
      "moneyScore": 4,
      "loveScore": 5,
      "workScore": 5,
      "healthScore": 4
    },
    {
      "date": "2026-05-05",
      "sign": "염소자리",
      "rank": 3,
      "shortMessage": "상쾌한 외출이 좋아요.",
      "detail": "신체와 마음이 모두 가벼운 외출을 하기 좋은 날이에요. 열린 공간에서 리프레시 해보세요. 바베큐나 하이킹을 만끽하면 좋아요.",
      "luckyColor": "은색",
      "luckyItem": "코티지",
      "moneyScore": 5,
      "loveScore": 3,
      "workScore": 4,
      "healthScore": 5
    },
    {
      "date": "2026-05-05",
      "sign": "물병자리",
      "rank": 4,
      "shortMessage": "즐거운 날이에요.",
      "detail": "사랑하는 사람의 라이브에 참여하면 기분이 아주 좋을 거예요. 원하던 굿즈도 손에 쥐게 될 것 같아요. 가족과 느긋한 휴일을 보내는 것도 좋아요.",
      "luckyColor": "파란색",
      "luckyItem": "소프트 아이스크림",
      "moneyScore": 5,
      "loveScore": 4,
      "workScore": 4,
      "healthScore": 3
    },
    {
      "date": "2026-05-05",
      "sign": "천칭자리",
      "rank": 5,
      "shortMessage": "가까운 데이트가 좋아요.",
      "detail": "여가와 데이트를 즐길 수 있는 날이에요. 가까운 곳에서 아직 가보지 않은 장소로 가보세요. 파트너와의 거리도 좁혀질 일이 생길 거예요.",
      "luckyColor": "금색",
      "luckyItem": "테라스 밭",
      "moneyScore": 3,
      "loveScore": 5,
      "workScore": 4,
      "healthScore": 3
    },
    {
      "date": "2026-05-05",
      "sign": "황소자리",
      "rank": 6,
      "shortMessage": "꿈의 메시지가 있어요.",
      "detail": "꿈 속에 중요한 메시지가 나타날 것 같아요. 기억하고 있다면 파편이라도 메모해 두세요. 침구나 밤옷을 새롭게 해보세요.",
      "luckyColor": "베이지색",
      "luckyItem": "전시회",
      "moneyScore": 3,
      "loveScore": 3,
      "workScore": 4,
      "healthScore": 4
    },
    {
      "date": "2026-05-05",
      "sign": "전갈자리",
      "rank": 7,
      "shortMessage": "지갑 조심이 필요해요.",
      "detail": "여행 중에 기분이 커지기 쉬워요. 지갑 사정이 나빠질 수 있어요. 선물을 사는 건 괜찮지만 충동 구매나 보상 구매는 자제하는 게 좋아요.",
      "luckyColor": "초록색",
      "luckyItem": "우키요에",
      "moneyScore": 2,
      "loveScore": 4,
      "workScore": 3,
      "healthScore": 4
    },
    {
      "date": "2026-05-05",
      "sign": "게자리",
      "rank": 8,
      "shortMessage": "부드럽게 지내세요.",
      "detail": "세심한 만큼 작은 점까지 신경 쓰기 쉬워요. 너무 신경 쓰면 긴장감이 고조될 수 있어요. 부드러운 분위기를 유지하는 것이 좋아요.",
      "luckyColor": "빨간색",
      "luckyItem": "쇼룸",
      "moneyScore": 4,
      "loveScore": 2,
      "workScore": 4,
      "healthScore": 2
    },
    {
      "date": "2026-05-05",
      "sign": "사수자리",
      "rank": 9,
      "shortMessage": "모험이 필요한 날이에요.",
      "detail": "타고난 모험심을 발휘하고 싶어져요. 미지의 분야에 도전해 조금씩 성과를 쌓아가세요. 주위 사람들에게도 좋은 영향을 줄 거예요.",
      "luckyColor": "회색",
      "luckyItem": "쇼부욕",
      "moneyScore": 2,
      "loveScore": 4,
      "workScore": 2,
      "healthScore": 3
    },
    {
      "date": "2026-05-05",
      "sign": "처녀자리",
      "rank": 10,
      "shortMessage": "갈등 피하는 게 좋아요.",
      "detail": "프라이드 때문에 트러블이 생길 수 있어요. 사소한 문제로 갈등하지 않도록 주의하세요. 먼저 양보하면 원만하게 해결될 수 있어요.",
      "luckyColor": "핑크색",
      "luckyItem": "교통 정보",
      "moneyScore": 2,
      "loveScore": 2,
      "workScore": 3,
      "healthScore": 3
    },
    {
      "date": "2026-05-05",
      "sign": "쌍둥이자리",
      "rank": 11,
      "shortMessage": "상대에 따라 달라요.",
      "detail": "함께 행동하는 사람에 따라 운명이 나뉘어질 거예요. 제멋대로에 휘둘리지 않도록 주의하세요. 심리적으로도 기복이 있을 수 있어요.",
      "luckyColor": "하늘색",
      "luckyItem": "오월 인형",
      "moneyScore": 3,
      "loveScore": 2,
      "workScore": 3,
      "healthScore": 1
    },
    {
      "date": "2026-05-05",
      "sign": "물고기자리",
      "rank": 12,
      "shortMessage": "소비에 주의해야 해요.",
      "detail": "신제품에 쉽게 끌리는 날이에요. 비싼 물건을 성급하게 구매하면 후회할 수 있어요. 구독 서비스나 정기 결제를 재검토하는 것도 고려해보세요.",
      "luckyColor": "보라색",
      "luckyItem": "클로버",
      "moneyScore": 1,
      "loveScore": 3,
      "workScore": 2,
      "healthScore": 2
    }
  ]
}